urwid/__init__.py
urwid/canvas.py
urwid/command_map.py
urwid/container.py
urwid/decoration.py
urwid/font.py
urwid/graphics.py
urwid/numedit.py
urwid/signals.py
urwid/split_repr.py
urwid/str_util.py
urwid/text_layout.py
urwid/util.py
urwid/version.py
urwid/vterm.py
urwid/wimp.py
urwid/display/__init__.py
urwid/display/_posix_raw_display.py
urwid/display/_raw_display_base.py
urwid/display/_web.css
urwid/display/_web.js
urwid/display/_win32.py
urwid/display/_win32_raw_display.py
urwid/display/common.py
urwid/display/curses.py
urwid/display/escape.py
urwid/display/html_fragment.py
urwid/display/lcd.py
urwid/display/raw.py
urwid/display/web.py
urwid/event_loop/__init__.py
urwid/event_loop/abstract_loop.py
urwid/event_loop/asyncio_loop.py
urwid/event_loop/glib_loop.py
urwid/event_loop/main_loop.py
urwid/event_loop/select_loop.py
urwid/event_loop/tornado_loop.py
urwid/event_loop/trio_loop.py
urwid/event_loop/twisted_loop.py
urwid/event_loop/zmq_loop.py
urwid/widget/__init__.py
urwid/widget/attr_map.py
urwid/widget/attr_wrap.py
urwid/widget/bar_graph.py
urwid/widget/big_text.py
urwid/widget/box_adapter.py
urwid/widget/columns.py
urwid/widget/constants.py
urwid/widget/container.py
urwid/widget/divider.py
urwid/widget/edit.py
urwid/widget/filler.py
urwid/widget/frame.py
urwid/widget/grid_flow.py
urwid/widget/line_box.py
urwid/widget/listbox.py
urwid/widget/monitored_list.py
urwid/widget/overlay.py
urwid/widget/padding.py
urwid/widget/pile.py
urwid/widget/popup.py
urwid/widget/progress_bar.py
urwid/widget/scrollable.py
urwid/widget/solid_fill.py
urwid/widget/text.py
urwid/widget/treetools.py
urwid/widget/widget.py
urwid/widget/widget_decoration.py
urwid/widget/wimp.py
urwid-3.0.1.dist-info/licenses/COPYING
urwid-3.0.1.dist-info/METADATA
urwid-3.0.1.dist-info/WHEEL
urwid-3.0.1.dist-info/top_level.txt
urwid-3.0.1.dist-info/RECORD
