Metadata-Version: 2.4
Name: urwid
Version: 3.0.1
Summary: A full-featured console (xterm et al.) user interface library
Author-email: Ian Ward <ian@excess.org>
License: LGPL-2.1-only
Project-URL: Homepage, https://urwid.org/
Project-URL: Documentation, https://urwid.org/manual/index.html
Project-URL: Repository, https://github.com/urwid/urwid
Project-URL: Bug Tracker, https://github.com/urwid/urwid/issues
Keywords: curses,ui,widget,scroll,listbox,user interface,text layout,console,ncurses
Platform: unix-like
Classifier: Development Status :: 5 - Production/Stable
Classifier: Environment :: Console
Classifier: Environment :: Console :: Curses
Classifier: Intended Audience :: Developers
Classifier: License :: OSI Approved :: GNU Library or Lesser General Public License (LGPL)
Classifier: Operating System :: POSIX
Classifier: Operating System :: Unix
Classifier: Operating System :: MacOS :: MacOS X
Classifier: Operating System :: Microsoft :: Windows
Classifier: Topic :: Software Development :: Libraries :: Python Modules
Classifier: Topic :: Software Development :: Widget Sets
Classifier: Programming Language :: Python :: 3
Classifier: Programming Language :: Python :: 3.9
Classifier: Programming Language :: Python :: 3.10
Classifier: Programming Language :: Python :: 3.11
Classifier: Programming Language :: Python :: 3.12
Classifier: Programming Language :: Python :: 3.13
Classifier: Programming Language :: Python :: 3 :: Only
Classifier: Programming Language :: Python :: Implementation :: CPython
Classifier: Programming Language :: Python :: Implementation :: PyPy
Requires-Python: >=3.9.0
License-File: COPYING
Requires-Dist: wcwidth
Provides-Extra: curses
Requires-Dist: windows-curses; sys_platform == "win32" and extra == "curses"
Provides-Extra: glib
Requires-Dist: PyGObject; extra == "glib"
Provides-Extra: tornado
Requires-Dist: tornado>=5.0; extra == "tornado"
Provides-Extra: trio
Requires-Dist: trio>=0.24.0; extra == "trio"
Requires-Dist: exceptiongroup; python_version < "3.11" and extra == "trio"
Provides-Extra: twisted
Requires-Dist: twisted; extra == "twisted"
Provides-Extra: zmq
Requires-Dist: zmq; extra == "zmq"
Provides-Extra: serial
Requires-Dist: pyserial; extra == "serial"
Provides-Extra: lcd
Requires-Dist: pyserial; extra == "lcd"
Dynamic: license-file
